swh/__init__.py
swh/web/__init__.py
swh/web/config.py
swh/web/doc_config.py
swh/web/gunicorn_config.py
swh/web/manage.py
swh/web/py.typed
swh/web/urls.py
swh/web/admin/__init__.py
swh/web/admin/adminurls.py
swh/web/admin/deposit.py
swh/web/admin/origin_save.py
swh/web/admin/urls.py
swh/web/api/__init__.py
swh/web/api/apidoc.py
swh/web/api/apiresponse.py
swh/web/api/apiurls.py
swh/web/api/renderers.py
swh/web/api/urls.py
swh/web/api/utils.py
swh/web/api/views/__init__.py
swh/web/api/views/content.py
swh/web/api/views/directory.py
swh/web/api/views/identifiers.py
swh/web/api/views/origin.py
swh/web/api/views/origin_save.py
swh/web/api/views/release.py
swh/web/api/views/revision.py
swh/web/api/views/snapshot.py
swh/web/api/views/stat.py
swh/web/api/views/utils.py
swh/web/api/views/vault.py
swh/web/assets/config/.bootstraprc
swh/web/assets/config/.eslintignore
swh/web/assets/config/.eslintrc
swh/web/assets/config/bootstrap-pre-customize.scss
swh/web/assets/config/mathjax-js-files.js
swh/web/assets/config/webpack.config.development.js
swh/web/assets/config/webpack.config.production.js
swh/web/assets/config/webpack-plugins/fix-swh-source-maps-webpack-plugin.js
swh/web/assets/config/webpack-plugins/generate-weblabels-webpack-plugin/README.md
swh/web/assets/config/webpack-plugins/generate-weblabels-webpack-plugin/index.js
swh/web/assets/config/webpack-plugins/generate-weblabels-webpack-plugin/jslicenses.ejs
swh/web/assets/config/webpack-plugins/generate-weblabels-webpack-plugin/plugin-options-schema.json
swh/web/assets/config/webpack-plugins/generate-weblabels-webpack-plugin/spdx-licenses-mapping.js
swh/web/assets/src/bundles/admin/deposit.js
swh/web/assets/src/bundles/admin/index.js
swh/web/assets/src/bundles/admin/origin-save.js
swh/web/assets/src/bundles/browse/breadcrumbs.css
swh/web/assets/src/bundles/browse/browse-utils.js
swh/web/assets/src/bundles/browse/browse.css
swh/web/assets/src/bundles/browse/content.css
swh/web/assets/src/bundles/browse/index.js
swh.web-0.0.223.dist-info/AUTHORS
swh.web-0.0.223.dist-info/LICENSE
swh.web-0.0.223.dist-info/METADATA
swh.web-0.0.223.dist-info/WHEEL
swh.web-0.0.223.dist-info/top_level.txt
swh.web-0.0.223.dist-info/RECORD
