Metadata-Version: 2.1
Name: swh.web
Version: 0.0.223
Summary: Software Heritage Web UI
Home-page: https://forge.softwareheritage.org/diffusion/DWUI/
Author: Software Heritage developers
Author-email: swh-devel@inria.fr
License: UNKNOWN
Project-URL: Bug Reports, https://forge.softwareheritage.org/maniphest
Project-URL: Funding, https://www.softwareheritage.org/donate
Project-URL: Source, https://forge.softwareheritage.org/source/swh-web
Platform: UNKNOWN
Classifier: Programming Language :: Python :: 3
Classifier: Intended Audience :: Developers
Classifier: License :: OSI Approved :: GNU Affero General Public License v3 or later (AGPLv3+)
Classifier: Operating System :: OS Independent
Classifier: Development Status :: 5 - Production/Stable
Classifier: Framework :: Django
Requires-Dist: beautifulsoup4
Requires-Dist: Django (<2.0,>=1.11.0)
Requires-Dist: django-cors-headers
Requires-Dist: djangorestframework (>=3.4.0)
Requires-Dist: django-webpack-loader
Requires-Dist: django-js-reverse
Requires-Dist: docutils
Requires-Dist: python-magic (>=0.4.0)
Requires-Dist: htmlmin
Requires-Dist: lxml
Requires-Dist: prometheus-client
Requires-Dist: pygments
Requires-Dist: pypandoc
Requires-Dist: python-dateutil
Requires-Dist: pyyaml
Requires-Dist: requests
Requires-Dist: python-memcached
Requires-Dist: pybadges
Requires-Dist: sentry-sdk
Requires-Dist: sphinx
Requires-Dist: sphinxcontrib-httpdomain
Requires-Dist: swh.model (>=0.0.32)
Requires-Dist: swh.storage (>=0.0.145)
Requires-Dist: swh.vault (>=0.0.23)
Requires-Dist: swh.indexer (>=0.0.120)
Requires-Dist: swh.scheduler (>=0.0.31)
Requires-Dist: swh.core (>=0.0.81)
Provides-Extra: testing
Requires-Dist: hypothesis ; extra == 'testing'
Requires-Dist: pytest ; extra == 'testing'
Requires-Dist: pytest-django ; extra == 'testing'
Requires-Dist: pytest-mock ; extra == 'testing'
Requires-Dist: django-stubs (<1.3.0) ; extra == 'testing'
Requires-Dist: requests-mock ; extra == 'testing'
Requires-Dist: swh.core[http] (>=0.0.81) ; extra == 'testing'
Requires-Dist: swh.loader.git (>=0.0.55) ; extra == 'testing'
Requires-Dist: decorator ; extra == 'testing'
